<?xml version="1.0" encoding="UTF-8"?>
<java version="1.8.0_251" class="java.beans.XMLDecoder">
 <object class="java.util.ArrayList">
  <void method="add">
   <string>09/06/2021 19:10:48 - Box: 1- DNI: 11111111 - Johnny Depp - Categoria: Premium</string>
  </void>
  <void method="add">
   <string>09/06/2021 19:10:49 - Box: 1- DNI: 22222222 - Tobey Maguire - Categoria: Plus</string>
  </void>
  <void method="add">
   <string>09/06/2021 19:11:19 - Box: 2- DNI: 33333333 - Andrew Garfield - Categoria: Normal</string>
  </void>
  <void method="add">
   <string>09/06/2021 19:11:23 - Box: 1- DNI: 44444444 - Emma Watson - Categoria: Premium</string>
  </void>
  <void method="add">
   <string>09/06/2021 19:11:42 - Box: 2- DNI: 55555555 - Chris Evans - Categoria: Normal</string>
  </void>
  <void method="add">
   <string>09/06/2021 19:11:44 - Box: 1- DNI: 66666666 - Christian Bale - Categoria: Basico</string>
  </void>
  <void method="add">
   <string>09/06/2021 19:14:01 - Box: 1- DNI: 77777777 - Heath Ledger - Categoria: Basico</string>
  </void>
  <void method="add">
   <string>09/06/2021 19:14:04 - Box: 1- DNI: 88888888 - Elizabeth Olsen - Categoria: Plus</string>
  </void>
  <void method="add">
   <string>09/06/2021 19:14:07 - Box: 2- DNI: 99999999 - Gary Oldman - Categoria: Premium</string>
  </void>
  <void method="add">
   <string>09/06/2021 19:14:11 - Box: 2- DNI: 12345678 - David Thewlis - Categoria: Premium</string>
  </void>
  <void method="add">
   <string>09/06/2021 19:14:13 - Box: 2- DNI: 11111111 - Johnny Depp - Categoria: Premium</string>
  </void>
  <void method="add">
   <string>09/06/2021 19:14:35 - Box: 2- DNI: 22222222 - Tobey Maguire - Categoria: Plus</string>
  </void>
  <void method="add">
   <string>09/06/2021 19:14:47 - Box: 2- DNI: 33333333 - Andrew Garfield - Categoria: Normal</string>
  </void>
  <void method="add">
   <string>09/06/2021 19:37:02 - Box: 1- DNI: 11111111 - Johnny Depp - Categoria: Premium</string>
  </void>
  <void method="add">
   <string>09/06/2021 19:37:05 - Box: 1- DNI: 22222222 - Tobey Maguire - Categoria: Plus</string>
  </void>
  <void method="add">
   <string>09/06/2021 19:37:30 - Box: 2- DNI: 33333333 - Andrew Garfield - Categoria: Normal</string>
  </void>
  <void method="add">
   <string>09/06/2021 19:37:33 - Box: 2- DNI: 44444444 - Emma Watson - Categoria: Premium</string>
  </void>
  <void method="add">
   <string>09/06/2021 19:37:34 - Box: 1- DNI: 55555555 - Chris Evans - Categoria: Normal</string>
  </void>
  <void method="add">
   <string>09/06/2021 19:38:22 - Box: 1- DNI: 66666666 - Christian Bale - Categoria: Basico</string>
  </void>
  <void method="add">
   <string>09/06/2021 19:38:24 - Box: 2- DNI: 77777777 - Heath Ledger - Categoria: Basico</string>
  </void>
  <void method="add">
   <string>09/06/2021 19:38:26 - Box: 2- DNI: 88888888 - Elizabeth Olsen - Categoria: Plus</string>
  </void>
  <void method="add">
   <string>09/06/2021 19:38:52 - Box: 1- DNI: 99999999 - Gary Oldman - Categoria: Premium</string>
  </void>
  <void method="add">
   <string>09/06/2021 19:38:53 - Box: 2- DNI: 12345678 - David Thewlis - Categoria: Premium</string>
  </void>
  <void method="add">
   <string>09/06/2021 19:39:25 - Box: 1- DNI: 11111111 - Johnny Depp - Categoria: Premium</string>
  </void>
  <void method="add">
   <string>09/06/2021 19:39:26 - Box: 2- DNI: 22222222 - Tobey Maguire - Categoria: Plus</string>
  </void>
  <void method="add">
   <string>10/06/2021 01:41:30 - Box: 1- DNI: 11111111 - Johnny Depp - Categoria: Premium</string>
  </void>
  <void method="add">
   <string>10/06/2021 01:41:31 - Box: 2- DNI: 22222222 - Tobey Maguire - Categoria: Plus</string>
  </void>
  <void method="add">
   <string>10/06/2021 01:43:12 - Box: 1- DNI: 33333333 - Andrew Garfield - Categoria: Normal</string>
  </void>
  <void method="add">
   <string>10/06/2021 01:43:15 - Box: 2- DNI: 44444444 - Emma Watson - Categoria: Premium</string>
  </void>
  <void method="add">
   <string>10/06/2021 01:43:53 - Box: 1- DNI: 55555555 - Chris Evans - Categoria: Normal</string>
  </void>
  <void method="add">
   <string>10/06/2021 01:43:56 - Box: 2- DNI: 77777777 - Heath Ledger - Categoria: Basico</string>
  </void>
  <void method="add">
   <string>10/06/2021 15:11:32 - Box: 1- DNI: 11111111 - Johnny Depp - Categoria: Premium</string>
  </void>
  <void method="add">
   <string>10/06/2021 15:11:33 - Box: 2- DNI: 22222222 - Tobey Maguire - Categoria: Plus</string>
  </void>
  <void method="add">
   <string>10/06/2021 15:13:05 - Box: 1- DNI: 33333333 - Andrew Garfield - Categoria: Normal</string>
  </void>
  <void method="add">
   <string>10/06/2021 15:13:09 - Box: 2- DNI: 44444444 - Emma Watson - Categoria: Premium</string>
  </void>
  <void method="add">
   <string>10/06/2021 15:14:25 - Box: 1- DNI: 55555555 - Chris Evans - Categoria: Normal</string>
  </void>
  <void method="add">
   <string>10/06/2021 15:46:08 - Box: 1- DNI: 11111111 - Johnny Depp - Categoria: Premium</string>
  </void>
  <void method="add">
   <string>10/06/2021 15:46:09 - Box: 2- DNI: 22222222 - Tobey Maguire - Categoria: Plus</string>
  </void>
  <void method="add">
   <string>10/06/2021 15:50:11 - Box: 1- DNI: 11111111 - Johnny Depp - Categoria: Premium</string>
  </void>
  <void method="add">
   <string>10/06/2021 15:50:11 - Box: 2- DNI: 22222222 - Tobey Maguire - Categoria: Plus</string>
  </void>
  <void method="add">
   <string>10/06/2021 15:58:06 - Box: 1- DNI: 11111111 - Johnny Depp - Categoria: Premium</string>
  </void>
  <void method="add">
   <string>10/06/2021 16:01:57 - Box: 1- DNI: 11111111 - Johnny Depp - Categoria: Premium</string>
  </void>
  <void method="add">
   <string>10/06/2021 16:07:30 - Box: 1- DNI: 11111111 - Johnny Depp - Categoria: Premium</string>
  </void>
  <void method="add">
   <string>10/06/2021 16:18:37 - Box: 5- DNI: 88888888 - Elizabeth Olsen - Categoria: Plus</string>
  </void>
  <void method="add">
   <string>10/06/2021 16:18:38 - Box: 5- DNI: 99999999 - Gary Oldman - Categoria: Premium</string>
  </void>
  <void method="add">
   <string>10/06/2021 16:18:38 - Box: 5- DNI: 12345678 - David Thewlis - Categoria: Premium</string>
  </void>
  <void method="add">
   <string>10/06/2021 16:30:16 - Box: 1- DNI: 11111111 - Johnny Depp - Categoria: Premium</string>
  </void>
  <void method="add">
   <string>11/06/2021 16:17:16 - Box: 1 - DNI: 11111111 - Johnny Depp - Categoria: Premium</string>
  </void>
  <void method="add">
   <string>11/06/2021 16:17:18 - Box: 1 - DNI: 22222222 - Tobey Maguire - Categoria: Plus</string>
  </void>
  <void method="add">
   <string>11/06/2021 16:17:19 - Box: 1 - DNI: 33333333 - Andrew Garfield - Categoria: Normal</string>
  </void>
  <void method="add">
   <string>11/06/2021 16:17:19 - Box: 1 - DNI: 44444444 - Emma Watson - Categoria: Premium</string>
  </void>
  <void method="add">
   <string>11/06/2021 16:17:20 - Box: 1 - DNI: 55555555 - Chris Evans - Categoria: Normal</string>
  </void>
  <void method="add">
   <string>11/06/2021 16:18:19 - Box: 1 - DNI: 11111111 - Johnny Depp - Categoria: Premium</string>
  </void>
  <void method="add">
   <string>11/06/2021 16:18:20 - Box: 1 - DNI: 88888888 - Elizabeth Olsen - Categoria: Plus</string>
  </void>
  <void method="add">
   <string>11/06/2021 16:27:17 - Box: 1 - DNI: 11111111 - Johnny Depp - Categoria: Premium</string>
  </void>
  <void method="add">
   <string>11/06/2021 16:39:11 - Box: 2 - DNI: 11111111 - Johnny Depp - Categoria: Premium</string>
  </void>
  <void method="add">
   <string>11/06/2021 16:39:13 - Box: 2 - DNI: 22222222 - Tobey Maguire - Categoria: Plus</string>
  </void>
  <void method="add">
   <string>11/06/2021 16:44:42 - Box: 2 - DNI: 11111111 - Johnny Depp - Categoria: Premium</string>
  </void>
  <void method="add">
   <string>11/06/2021 16:44:43 - Box: 2 - DNI: 22222222 - Tobey Maguire - Categoria: Plus</string>
  </void>
  <void method="add">
   <string>11/06/2021 16:45:44 - Box: 2 - DNI: 33333333 - Andrew Garfield - Categoria: Normal</string>
  </void>
  <void method="add">
   <string>11/06/2021 16:45:46 - Box: 2 - DNI: 44444444 - Emma Watson - Categoria: Premium</string>
  </void>
  <void method="add">
   <string>11/06/2021 16:45:47 - Box: 2 - DNI: 55555555 - Chris Evans - Categoria: Normal</string>
  </void>
  <void method="add">
   <string>11/06/2021 16:45:47 - Box: 2 - DNI: 66666666 - Christian Bale - Categoria: Basico</string>
  </void>
  <void method="add">
   <string>11/06/2021 16:45:48 - Box: 2 - DNI: 77777777 - Heath Ledger - Categoria: Basico</string>
  </void>
  <void method="add">
   <string>11/06/2021 16:45:48 - Box: 2 - DNI: 88888888 - Elizabeth Olsen - Categoria: Plus</string>
  </void>
  <void method="add">
   <string>11/06/2021 16:45:49 - Box: 2 - DNI: 99999999 - Gary Oldman - Categoria: Premium</string>
  </void>
  <void method="add">
   <string>11/06/2021 16:45:50 - Box: 2 - DNI: 12345678 - David Thewlis - Categoria: Premium</string>
  </void>
  <void method="add">
   <string>11/06/2021 16:48:52 - Box: 3 - DNI: 11111111 - Johnny Depp - Categoria: Premium</string>
  </void>
  <void method="add">
   <string>11/06/2021 16:48:53 - Box: 3 - DNI: 22222222 - Tobey Maguire - Categoria: Plus</string>
  </void>
  <void method="add">
   <string>11/06/2021 16:57:13 - Box: 2 - DNI: 11111111 - Johnny Depp - Categoria: Premium</string>
  </void>
  <void method="add">
   <string>11/06/2021 16:57:46 - Box: 2 - DNI: 22222222 - Tobey Maguire - Categoria: Plus</string>
  </void>
  <void method="add">
   <string>11/06/2021 16:57:47 - Box: 2 - DNI: 33333333 - Andrew Garfield - Categoria: Normal</string>
  </void>
  <void method="add">
   <string>11/06/2021 16:57:47 - Box: 2 - DNI: 44444444 - Emma Watson - Categoria: Premium</string>
  </void>
  <void method="add">
   <string>11/06/2021 16:57:48 - Box: 2 - DNI: 12345678 - David Thewlis - Categoria: Premium</string>
  </void>
  <void method="add">
   <string>11/06/2021 17:05:55 - Box: 2 - DNI: 11111111 - Johnny Depp - Categoria: Premium</string>
  </void>
  <void method="add">
   <string>11/06/2021 17:06:21 - Box: 2 - DNI: 11111111 - Johnny Depp - Categoria: Premium</string>
  </void>
  <void method="add">
   <string>11/06/2021 17:06:22 - Box: 2 - DNI: 99999999 - Gary Oldman - Categoria: Premium</string>
  </void>
  <void method="add">
   <string>11/06/2021 17:06:43 - Box: 2 - DNI: 88888888 - Elizabeth Olsen - Categoria: Plus</string>
  </void>
  <void method="add">
   <string>11/06/2021 17:06:44 - Box: 2 - DNI: 11111111 - Johnny Depp - Categoria: Premium</string>
  </void>
 </object>
</java>
